{
  "name": "Fog Cloud",
  "description": "You create a 20-foot-radius sphere of fog centered on a point within range. The sphere spreads around corners, and its area is heavily obscured. It lasts for the duration or until a wind of moderate or greater speed (at least 10 miles per hour) disperses it.",
  "action_type": "action",
  "range": 120,
  "requires_concentration": true,
  "ai_priority": 5,
  "spell_level": 1,
  "resource_cost": {
    "spell_slot_1": 1
  },
  "target_type": "area_sphere",
  "area_size": 20,
  "obscuring_zone": "fog"
}